imagewiz/__init__.py
imagewiz/fw.py
imagewiz/he.py
imagewiz/imagewiz.py
imagewiz-0.9.dist-info/LICENSE
imagewiz-0.9.dist-info/METADATA
imagewiz-0.9.dist-info/WHEEL
imagewiz-0.9.dist-info/top_level.txt
imagewiz-0.9.dist-info/RECORD
