Metadata-Version: 2.1
Name: imagewiz
Version: 0.9
Summary: A image preprocessing module to compliment Tensorflow/Keras
Home-page: https://github.com/DuoFinch/imagewiz
Author: Evan Gibson
Author-email: evan.gibson@duofinch.com
License: UNKNOWN
Platform: UNKNOWN
Classifier: Development Status :: 3 - Alpha
Classifier: Programming Language :: Python :: 3
Classifier: License :: OSI Approved :: MIT License
Classifier: Operating System :: OS Independent
Classifier: Topic :: Scientific/Engineering :: Image Recognition
Requires-Dist: pydicom
Requires-Dist: pypng
Requires-Dist: tqdm
